easyscience/__init__.py
easyscience/__version__.py
easyscience/base_classes/__init__.py
easyscience/base_classes/based_base.py
easyscience/base_classes/collection_base.py
easyscience/base_classes/obj_base.py
easyscience/fitting/__init__.py
easyscience/fitting/available_minimizers.py
easyscience/fitting/fitter.py
easyscience/fitting/multi_fitter.py
easyscience/fitting/calculators/__init__.py
easyscience/fitting/calculators/interface_factory.py
easyscience/fitting/minimizers/__init__.py
easyscience/fitting/minimizers/factory.py
easyscience/fitting/minimizers/minimizer_base.py
easyscience/fitting/minimizers/minimizer_bumps.py
easyscience/fitting/minimizers/minimizer_dfo.py
easyscience/fitting/minimizers/minimizer_lmfit.py
easyscience/fitting/minimizers/utils.py
easyscience/global_object/__init__.py
easyscience/global_object/global_object.py
easyscience/global_object/logger.py
easyscience/global_object/map.py
easyscience/global_object/undo_redo.py
easyscience/global_object/hugger/__init__.py
easyscience/global_object/hugger/hugger.py
easyscience/global_object/hugger/property.py
easyscience/io/__init__.py
easyscience/io/serializer_base.py
easyscience/io/serializer_component.py
easyscience/io/serializer_dict.py
easyscience/job/__init__.py
easyscience/job/analysis.py
easyscience/job/experiment.py
easyscience/job/job.py
easyscience/job/theoreticalmodel.py
easyscience/models/__init__.py
easyscience/models/polynomial.py
easyscience/utils/__init__.py
easyscience/utils/classTools.py
easyscience/utils/classUtils.py
easyscience/utils/decorators.py
easyscience/utils/string.py
easyscience/variable/__init__.py
easyscience/variable/descriptor_any_type.py
easyscience/variable/descriptor_array.py
easyscience/variable/descriptor_base.py
easyscience/variable/descriptor_bool.py
easyscience/variable/descriptor_number.py
easyscience/variable/descriptor_str.py
easyscience/variable/parameter.py
easyscience-2.0.0.dist-info/METADATA
easyscience-2.0.0.dist-info/WHEEL
easyscience-2.0.0.dist-info/licenses/LICENSE
easyscience-2.0.0.dist-info/RECORD
