Metadata-Version: 2.1
Name: easyscience
Version: 2.0.0
Summary: Generic logic for easyScience libraries
Project-URL: homepage, https://github.com/EasyScience/EasyScience
Project-URL: documentation, https://easyscience.github.io/EasyScience/
Author: EasyScience contributors
License: BSD 3-Clause License
License-File: LICENSE
Classifier: Development Status :: 3 - Alpha
Classifier: License :: OSI Approved :: BSD License
Classifier: Operating System :: OS Independent
Classifier: Programming Language :: Python :: 3
Classifier: Programming Language :: Python :: 3 :: Only
Classifier: Programming Language :: Python :: 3.11
Classifier: Programming Language :: Python :: 3.12
Classifier: Programming Language :: Python :: 3.13
Classifier: Topic :: Scientific/Engineering
Requires-Python: >=3.11
Requires-Dist: asteval
Requires-Dist: bumps
Requires-Dist: dfo-ls
Requires-Dist: lmfit
Requires-Dist: numpy
Requires-Dist: scipp
Requires-Dist: uncertainties
Provides-Extra: dev
Requires-Dist: build; extra == 'dev'
Requires-Dist: codecov; extra == 'dev'
Requires-Dist: flake8; extra == 'dev'
Requires-Dist: matplotlib; extra == 'dev'
Requires-Dist: pytest; extra == 'dev'
Requires-Dist: pytest-cov; extra == 'dev'
Requires-Dist: ruff; extra == 'dev'
Requires-Dist: tox-gh-actions; extra == 'dev'
Provides-Extra: docs
Requires-Dist: doc8; extra == 'docs'
Requires-Dist: readme-renderer; extra == 'docs'
Requires-Dist: sphinx-autodoc-typehints; extra == 'docs'
Requires-Dist: sphinx-book-theme; extra == 'docs'
Requires-Dist: sphinx-gallery; extra == 'docs'
Requires-Dist: toml; extra == 'docs'
